8-bit ALU using dataflow/bit8_ALU.v
module alu_8bit (
    input [7:0] A,
    input [7:0] B,
    input [2:0] ALU_Sel,  // ALU operation selector
    output [7:0] ALU_out,  // Result
    output Carryout  // Carry out flag
);

  wire [7:0] sum, diff, and_res, or_res, xor_res, shift_left, shift_right, not_a;
  wire carry_sum, borrow_diff;

  assign {carry_sum, sum} = A + B;
  assign {borrow_diff, diff} = A - B;

  assign and_res = A & B;
  assign or_res = A | B;
  assign xor_res = A ^ B;
  assign not_a = ~A;

  assign shift_left = {A[6:0],A[0]};
  assign shift_right = {A[7],A[7:1]};


  assign ALU_out = (ALU_Sel == 3'b000) ? sum:
  (ALU_Sel == 3'b001) ? diff:
  (ALU_Sel == 3'b010) ? and_res:
  (ALU_Sel == 3'b011) ? or_res:
  (ALU_Sel == 3'b100) ? xor_res:
  (ALU_Sel == 3'b101) ? shift_left:
  (ALU_Sel == 3'b110) ? shift_right:
  (ALU_Sel == 3'b111) ? not_a:8'b0;

  assign Carryout  = (ALU_Sel == 3'b000) ? carry_sum:
  (ALU_Sel == 3'b001) ? borrow_diff: 1'b0;
  
endmodule

8-bit ALU/bit8_ALU_tb.v
`timescale 1ns/1ps

module alu_8bit_tb;
  
  reg [7:0] A,B;
  reg [2:0] ALU_Sel;

  wire [7:0] ALU_out;
  wire Carryout;

  alu_8bit uut(
    .A(A),
    .B(B),
    .ALU_Sel(ALU_Sel),
    .ALU_out(ALU_out),
    .Carryout(Carryout)
  );

  initial begin
    $dumpfile("alu_8bit.vcd");
    $dumpvars(0,uut);

    // Addition
    A = 8'hFF; B=8'h01; ALU_Sel = 3'b000;
    #100;

    // Subraction
    A = 8'h00; B=8'h01; ALU_Sel = 3'b001;
    #100;

    // AND
    A = 8'hF0; B=8'h0F; ALU_Sel = 3'b010;
    #100;

    // OR 
    A = 8'hF0; B=8'h0F; ALU_Sel = 3'b011;
    #100;

    // Shift left
    A = 8'h80; B=8'h00; ALU_Sel = 3'b101;
    #100;

    // XOR 
    A = 8'hFF; B=8'h55; ALU_Sel = 3'b100;
    #100;

    // Shift right 
    A = 8'h01; B=8'h00; ALU_Sel = 3'b110;
    #100;

    // A complement
    A = 8'hFF; B=8'h00; ALU_Sel = 3'b111;
    #100;


end 
endmodule

8-bit ALU using dataflow/alu_8bit.vcd
$date
	Thu Jun 25 15:30:22 2026
$end
$version
	Icarus Verilog
$end
$timescale
	1ps
$end
$scope module alu_8bit_tb $end
$scope module uut $end
$var wire 8 ! A [7:0] $end
$var wire 3 " ALU_Sel [2:0] $end
$var wire 8 # B [7:0] $end
$var wire 8 $ and_res [7:0] $end
$var wire 8 % not_a [7:0] $end
$var wire 8 & or_res [7:0] $end
$var wire 8 ' xor_res [7:0] $end
$var wire 8 ( sum [7:0] $end
$var wire 8 ) shift_right [7:0] $end
$var wire 8 * shift_left [7:0] $end
$var wire 8 + diff [7:0] $end
$var wire 1 , carry_sum $end
$var wire 1 - borrow_diff $end
$var wire 1 . Carryout $end
$var wire 8 / ALU_out [7:0] $end
$upscope $end
$upscope $end
$enddefinitions $end
$comment Show the parameter values. $end
$dumpall
$end
#0
$dumpvars
b0 /
1.
0-
1,
b11111110 +
b11111111 *
b11111111 )
b0 (
b11111110 '
b11111111 &
b0 %
b1 $
b1 #
b0 "
b11111111 !
$end
#100000
b1 (
0,
b11111111 +
1-
b0 *
b0 )
b11111111 /
1.
b0 $
b1 &
b1 '
b11111111 %
b1 "
b0 !
#200000
b0 /
0.
b11111111 (
b11100001 +
0-
b11100000 *
b11111000 )
b11111111 &
b11111111 '
b1111 %
b10 "
b1111 #
b11110000 !
#300000
b11111111 /
b11 "
#400000
b0 /
b10000000 (
b10000000 +
b0 *
b11000000 )
b10000000 &
b10000000 '
b1111111 %
b101 "
b0 #
b10000000 !
#500000
b10101010 /
1,
b1010100 (
b10101010 +
b11111111 *
b11111111 )
b1010101 $
b11111111 &
b10101010 '
b0 %
b100 "
b1010101 #
b11111111 !
#600000
b0 /
b1 (
0,
b1 +
b11 *
b0 )
b0 $
b1 &
b1 '
b11111110 %
b110 "
b0 #
b1 !
#700000
b11111111 (
b11111111 +
b11111111 *
b11111111 )
b11111111 &
b11111111 '
b0 %
b111 "
b11111111 !
