8-bit adder/full_adder.v
module full_adder (
    input  a,
    b,
    cin,
    output sum,
    cout

);

  assign sum  = a ^ b ^ cin;
  assign cout = (a & b) | (b & cin) | (a & cin);
endmodule

8-bit adder/bit4_carry_adder.v
// 4-bit Adder using structural modeling with full adders
module adder_4bit (
    input [3:0] a, b,
    input cin,
    output [3:0] sum,
    output cout
);
    
    // Internal carry signals
    wire c1, c2, c3;
    
    // Instantiate 4 full adders structurally
    full_adder fa0 (
        .a(a[0]),
        .b(b[0]),
        .cin(cin),
        .sum(sum[0]),
        .cout(c1)
    );
    
    full_adder fa1 (
        .a(a[1]),
        .b(b[1]),
        .cin(c1),
        .sum(sum[1]),
        .cout(c2)
    );
    
    full_adder fa2 (
        .a(a[2]),
        .b(b[2]),
        .cin(c2),
        .sum(sum[2]),
        .cout(c3)
    );
    
    full_adder fa3 (
        .a(a[3]),
        .b(b[3]),
        .cin(c3),
        .sum(sum[3]),
        .cout(cout)
    );
    
endmodule

8-bit adder/bit8_adder.v
// 8-bit Adder using structural modeling with 4-bit adders
module adder_8bit (
    input [7:0] a, b,
    input cin,
    output [7:0] sum,
    output cout
);
    
    // Internal carry signal
    wire c4;
    
    // Instantiate two 4-bit adders
    adder_4bit adder_low (
        .a(a[3:0]),
        .b(b[3:0]),
        .cin(cin),
        .sum(sum[3:0]),
        .cout(c4)
    );
    
    adder_4bit adder_high (
        .a(a[7:4]),
        .b(b[7:4]),
        .cin(c4),
        .sum(sum[7:4]),
        .cout(cout)
    );
    
endmodule

8-bit adder/bit8_adder_tb.v
`timescale 1ns / 1ps

module bit8_adder_tb;

  // Inputs
  reg [7:0] a, b;
  reg cin;

  // Outputs
  wire [7:0] sum;
  wire cout;

  // Instantiate the 8-bit adder
  adder_8bit uut (
      .a(a),
      .b(b),
      .cin(cin),
      .sum(sum),
      .cout(cout)
  );

  // Test procedure
  initial begin
    $dumpfile("bit8_adder.vcd");
    $dumpvars(0, uut);

    // Test Case 1: Basic addition
    a   = 8'h05;
    b   = 8'h03;
    cin = 1'b0;
    #100;

    // Test Case 2: Addition with carry in
    a   = 8'h0A;
    b   = 8'h0F;
    cin = 1'b1;
    #100;

    // Test Case 3: Addition with carry out
    a   = 8'hFF;
    b   = 8'h01;
    cin = 1'b0;
    #100;

    // Test Case 4: Maximum addition
    a   = 8'hFF;
    b   = 8'hFF;
    cin = 1'b1;
    #100;

    // Test Case 5: Random test 1
    a   = 8'h3C;
    b   = 8'h4A;
    cin = 1'b0;
    #100;

    // Test Case 6: Random test 2
    a   = 8'h99;
    b   = 8'h66;
    cin = 1'b1;
    #100;

    // Test Case 7: Zero addition
    a   = 8'h00;
    b   = 8'h00;
    cin = 1'b0;
    #100;

    // Test Case 8: Crossing 8-bit boundary
    a   = 8'h80;
    b   = 8'h80;
    cin = 1'b0;
    #100;

    $finish;
  end

endmodule

8-bit adder/bit8_adder.vcd
$date
	Thu Jun 18 20:30:08 2026
$end
$version
	Icarus Verilog
$end
$timescale
	1ps
$end
$scope module bit8_adder_tb $end
$scope module uut $end
$var wire 8 ! a [7:0] $end
$var wire 8 " b [7:0] $end
$var wire 1 # cin $end
$var wire 8 $ sum [7:0] $end
$var wire 1 % cout $end
$var wire 1 & c4 $end
$scope module adder_high $end
$var wire 4 ' a [3:0] $end
$var wire 4 ( b [3:0] $end
$var wire 4 ) sum [3:0] $end
$var wire 1 % cout $end
$var wire 1 & cin $end
$var wire 1 * c3 $end
$var wire 1 + c2 $end
$var wire 1 , c1 $end
$scope module fa0 $end
$var wire 1 - a $end
$var wire 1 . b $end
$var wire 1 , cout $end
$var wire 1 / sum $end
$var wire 1 & cin $end
$upscope $end
$scope module fa1 $end
$var wire 1 0 a $end
$var wire 1 1 b $end
$var wire 1 , cin $end
$var wire 1 + cout $end
$var wire 1 2 sum $end
$upscope $end
$scope module fa2 $end
$var wire 1 3 a $end
$var wire 1 4 b $end
$var wire 1 + cin $end
$var wire 1 * cout $end
$var wire 1 5 sum $end
$upscope $end
$scope module fa3 $end
$var wire 1 6 a $end
$var wire 1 7 b $end
$var wire 1 * cin $end
$var wire 1 % cout $end
$var wire 1 8 sum $end
$upscope $end
$upscope $end
$scope module adder_low $end
$var wire 4 9 a [3:0] $end
$var wire 4 : b [3:0] $end
$var wire 1 # cin $end
$var wire 4 ; sum [3:0] $end
$var wire 1 & cout $end
$var wire 1 < c3 $end
$var wire 1 = c2 $end
$var wire 1 > c1 $end
$scope module fa0 $end
$var wire 1 ? a $end
$var wire 1 @ b $end
$var wire 1 # cin $end
$var wire 1 > cout $end
$var wire 1 A sum $end
$upscope $end
$scope module fa1 $end
$var wire 1 B a $end
$var wire 1 C b $end
$var wire 1 > cin $end
$var wire 1 = cout $end
$var wire 1 D sum $end
$upscope $end
$scope module fa2 $end
$var wire 1 E a $end
$var wire 1 F b $end
$var wire 1 = cin $end
$var wire 1 < cout $end
$var wire 1 G sum $end
$upscope $end
$scope module fa3 $end
$var wire 1 H a $end
$var wire 1 I b $end
$var wire 1 < cin $end
$var wire 1 & cout $end
$var wire 1 J sum $end
$upscope $end
$upscope $end
$upscope $end
$upscope $end
$enddefinitions $end
$comment Show the parameter values. $end
$dumpall
$end
#0
$dumpvars
1J
0I
0H
0G
0F
1E
0D
1C
0B
0A
1@
1?
1>
1=
1<
b1000 ;
b11 :
b101 9
08
07
06
05
04
03
02
01
00
0/
0.
0-
0,
0+
0*
b0 )
b0 (
b0 '
0&
0%
b1000 $
0#
b11 "
b101 !
$end
#100000
b1 )
1J
1/
1D
1<
1&
b11010 $
b1010 ;
1F
1I
0?
1B
0E
1H
0A
b1111 :
b1010 9
1#
b1111 "
b1010 !
#200000
1%
1&
1*
1<
0G
0D
1+
1=
b0 )
0J
0/
1,
02
05
08
b0 $
1>
b0 ;
0C
0F
0I
1?
1E
1-
10
13
16
0A
b1 :
b1111 9
b1111 '
0#
b1 "
b11111111 !
#300000
b1111 )
1D
1G
1J
1/
12
15
18
b11111111 $
b1111 ;
1C
1F
1I
1.
11
14
17
1A
b1111 :
b1111 (
1#
b11111111 "
#400000
0J
0<
0=
0>
b1000 )
0%
1G
0/
02
1D
05
b10000110 $
b110 ;
0@
0F
0.
01
07
0?
0B
03
06
0A
b1010 :
b100 (
b1100 9
b11 '
0#
b1001010 "
b111100 !
#500000
1<
02
0G
1,
1=
1*
0/
1&
0D
05
b0 )
0J
1>
1+
08
1%
b0 $
b0 ;
1F
0I
11
1?
0E
00
16
0A
b110 :
b110 (
b1001 9
b1001 '
1#
b1100110 "
b10011001 !
#600000
0=
0<
0+
0*
b0 )
0G
05
0J
0&
0/
0,
08
0%
b0 $
b0 ;
0>
0C
0F
01
04
0?
0H
0-
06
0A
b0 :
b0 (
b0 9
b0 '
0#
b0 "
b0 !
#700000
1%
17
16
b1000 (
b1000 '
b10000000 "
b10000000 !
