half adder/half_adder.v
module half_adder(
  input a,b,
  output sum, cout 
);
assign sum = a^b;
assign cout = a&b;

endmodule;

full adder/full_adder.v
module full_adder(
  input a,b,c,
  output sum, cout 
);
wire o1,o2,o3,o4;

half_adder ha1(
  .a(a),
  .b(b),
  .sum(o1),
  .cout(o2)
);
half_adder ha2(
  .a(o1),
  .b(c),
  .sum(o4),
  .cout(o3)
);

assign sum=o4;
assign cout = o3|o2;

endmodule;

full adder/full_adder_tb.v
`timescale 1ns/1ps

module full_adder_tb;
  reg a;
  reg b;
  reg c;
  wire sum;
  wire cout;

  full_adder uut(
    .a(a),
    .b(b),
    .c(c),
    .sum(sum),
    .cout(cout)
  );

  initial begin

    $dumpfile("full_adder.vcd");
    $dumpvars(0,uut);
 
    a=0;
    b=0;
    c=0;
    #100;
    
    a = 0;
    b = 1;
    c = 0;
    #100;

    a = 1;
    b = 0;
    c = 0;
    #100;

    a = 1;
    b = 1;
    c = 0;
    #100;


    a=0;
    b=0;
    c=1;
    #100;
    
    a = 0;
    b = 1;
    c = 1;
    #100;

    a = 1;
    b = 0; 
    c = 1;
    #100;

    a = 1;
    b = 1; 
    c = 1;
    #100;


end
endmodule

full adder/full_adder.vcd
$date
	Thu Jun 18 15:46:37 2026
$end
$version
	Icarus Verilog
$end
$timescale
	1ps
$end
$scope module full_adder_tb $end
$scope module uut $end
$var wire 1 ! a $end
$var wire 1 " b $end
$var wire 1 # c $end
$var wire 1 $ cout $end
$var wire 1 % sum $end
$var wire 1 & o4 $end
$var wire 1 ' o3 $end
$var wire 1 ( o2 $end
$var wire 1 ) o1 $end
$scope module ha1 $end
$var wire 1 ! a $end
$var wire 1 " b $end
$var wire 1 ( cout $end
$var wire 1 ) sum $end
$upscope $end
$scope module ha2 $end
$var wire 1 ) a $end
$var wire 1 # b $end
$var wire 1 ' cout $end
$var wire 1 & sum $end
$upscope $end
$upscope $end
$upscope $end
$enddefinitions $end
$comment Show the parameter values. $end
$dumpall
$end
#0
$dumpvars
0)
0(
0'
0&
0%
0$
0#
0"
0!
$end
#100000
1%
1&
1)
1"
#200000
0"
1!
#300000
0%
0&
1$
0)
1(
1"
#400000
0$
1%
1&
0(
1#
0"
0!
#500000
1$
0%
0&
1'
1)
1"
#600000
0"
1!
#700000
1%
1&
0'
0)
1(
1"
